beswarm/__init__.py
beswarm/broker.py
beswarm/cli.py
beswarm/core.py
beswarm/knowledge_graph.py
beswarm/prompt.py
beswarm/taskmanager.py
beswarm/utils.py
beswarm/agents/chatgroup.py
beswarm/agents/planact.py
beswarm/aient/aient/__init__.py
beswarm/aient/aient/architext/architext/__init__.py
beswarm/aient/aient/architext/architext/core.py
beswarm/aient/aient/architext/test/openai_client.py
beswarm/aient/aient/architext/test/test.py
beswarm/aient/aient/architext/test/test_save_load.py
beswarm/aient/aient/core/__init__.py
beswarm/aient/aient/core/log_config.py
beswarm/aient/aient/core/models.py
beswarm/aient/aient/core/request.py
beswarm/aient/aient/core/response.py
beswarm/aient/aient/core/utils.py
beswarm/aient/aient/core/test/test_base_api.py
beswarm/aient/aient/core/test/test_geminimask.py
beswarm/aient/aient/core/test/test_image.py
beswarm/aient/aient/core/test/test_payload.py
beswarm/aient/aient/models/__init__.py
beswarm/aient/aient/models/audio.py
beswarm/aient/aient/models/base.py
beswarm/aient/aient/models/chatgpt.py
beswarm/aient/aient/plugins/__init__.py
beswarm/aient/aient/plugins/arXiv.py
beswarm/aient/aient/plugins/config.py
beswarm/aient/aient/plugins/excute_command.py
beswarm/aient/aient/plugins/get_time.py
beswarm/aient/aient/plugins/image.py
beswarm/aient/aient/plugins/list_directory.py
beswarm/aient/aient/plugins/read_image.py
beswarm/aient/aient/plugins/readonly.py
beswarm/aient/aient/plugins/registry.py
beswarm/aient/aient/plugins/run_python.py
beswarm/aient/aient/plugins/websearch.py
beswarm/aient/aient/utils/__init__.py
beswarm/aient/aient/utils/prompt.py
beswarm/aient/aient/utils/scripts.py
beswarm/aient/test/test_Web_crawler.py
beswarm/aient/test/test_ddg_search.py
beswarm/aient/test/test_google_search.py
beswarm/aient/test/test_ollama.py
beswarm/aient/test/test_plugin.py
beswarm/aient/test/test_url.py
beswarm/aient/test/test_whisper.py
beswarm/bemcp/bemcp/__init__.py
beswarm/bemcp/bemcp/decorator.py
beswarm/bemcp/bemcp/main.py
beswarm-0.3.23.dist-info/METADATA
beswarm-0.3.23.dist-info/WHEEL
beswarm-0.3.23.dist-info/entry_points.txt
beswarm-0.3.23.dist-info/top_level.txt
beswarm-0.3.23.dist-info/RECORD
