Metadata-Version: 2.4
Name: beswarm
Version: 0.3.23
Summary: MAS
Requires-Python: >=3.11
Requires-Dist: chardet>=5.2.0
Requires-Dist: diskcache>=5.6.3
Requires-Dist: fake-useragent>=2.2.0
Requires-Dist: fastapi>=0.115.12
Requires-Dist: grep-ast>=0.8.1
Requires-Dist: httpx>=0.28.1
Requires-Dist: httpx-socks>=0.10.0
Requires-Dist: mcp[cli]>=1.9.4
Requires-Dist: msgspec>=0.19.0
Requires-Dist: networkx>=3.4.2
Requires-Dist: numpy>=2.2.5
Requires-Dist: pdfminer-six==20240706
Requires-Dist: pillow>=10.4.0
Requires-Dist: pyautogui>=0.9.54
Requires-Dist: pygments>=2.19.1
Requires-Dist: pyperclip>=1.9.0
Requires-Dist: pytz>=2025.2
Requires-Dist: reaktiv>=0.15.1
Requires-Dist: requests>=2.32.3
Requires-Dist: scipy>=1.15.3
Requires-Dist: tqdm>=4.67.1
Provides-Extra: search
Requires-Dist: beautifulsoup4>=4.13.4; extra == "search"
Requires-Dist: duckduckgo-search==5.3.1; extra == "search"
Requires-Dist: html2text>=2025.4.15; extra == "search"
Requires-Dist: lxml-html-clean>=0.4.2; extra == "search"
